talisestools/__init__.py
talisestools-0.0.12.dist-info/LICENSE
talisestools-0.0.12.dist-info/METADATA
talisestools-0.0.12.dist-info/WHEEL
talisestools-0.0.12.dist-info/top_level.txt
talisestools-0.0.12.dist-info/RECORD
